MANIFEST.in
setup.py
pyFresnel/COPYING
pyFresnel/README
pyFresnel/__init__.py
pyFresnel/constants.py
pyFresnel/effective_medium.py
pyFresnel/fresnel.py
pyFresnel/materials.py
pyFresnel/optical_plate.py
pyFresnel/pyFresnel.pdf
pyFresnel/uniaxial_plate.py
pyFresnel/uniaxial_plate2.py
pyFresnel/blogger/Thumbs.db
pyFresnel/blogger/Absorption by a Stack of Slabs (3)/Anisotropic_ThinFilm_example.py
pyFresnel/blogger/Absorption by a Stack of Slabs (3)/Thumbs.db
pyFresnel/blogger/Absorption by a Stack of Slabs (3)/Transfer_Matrix.py
pyFresnel/blogger/Absorption by a Stack of Slabs (3)/Uniaxial_Thin_Film.png
pyFresnel/blogger/Absorption by a Stack of Slabs (3)/Uniaxial_Thin_Film.svg
pyFresnel/blogger/Absorption by a Stack of Slabs (3)/Uniaxial_Thin_Film_spectra.png
pyFresnel/blogger/Absorption by a Stack of Slabs (3)/matplotlibrc
pyFresnel/blogger/Effective Medium/Effective Medium.zip
pyFresnel/blogger/Effective Medium/Effective_Medium_Thin_Film.svg
pyFresnel/blogger/Effective Medium/Effective_Medium_example.png
pyFresnel/blogger/Effective Medium/Effective_Medium_example_B.png
pyFresnel/blogger/Effective Medium/Thumbs.db
pyFresnel/blogger/Effective Medium/Transfer_Matrix.py
pyFresnel/blogger/Effective Medium/Uniaxial_Plate2.py
pyFresnel/blogger/Effective Medium/effective_medium.py
pyFresnel/blogger/Effective Medium/material_class.py
pyFresnel/blogger/Optical Absorption by a Slab (1)/Thumbs.db
pyFresnel/blogger/Optical Absorption by a Slab (1)/slab_abs_45degl_inc.png
pyFresnel/blogger/Optical Absorption by a Slab (1)/slab_abs_45degl_inc.svg
pyFresnel/blogger/Optical Absorption by a Slab (1)/slab_abs_45degl_inc_b.png
pyFresnel/blogger/Optical Absorption by a Slab (1)/slab_abs_45degl_inc_c.png
pyFresnel/blogger/Optical Absorption by a Slab (1)/slab_abs_normal_inc.png
pyFresnel/blogger/Optical Absorption by a Slab (1)/slab_abs_normal_inc.svg
pyFresnel/blogger/Optical Absorption by a Slab (1)/slab_abs_normal_inc_b.png
pyLuminous.egg-info/PKG-INFO
pyLuminous.egg-info/SOURCES.txt
pyLuminous.egg-info/dependency_links.txt
pyLuminous.egg-info/not-zip-safe
pyLuminous.egg-info/top_level.txt
