Metadata-Version: 1.1
Name: pyLuminous
Version: 0.8
Summary: Optical Transfer Matrix and simple Quantum Well modelling
Home-page: https://sourceforge.net/projects/pyluminous/
Author: robochat
Author-email: rjsteed@talk21.com
License: GPLv3
Keywords: optics optical transfer matrix quantum light
Platform: UNKNOWN
Classifier: License :: OSI Approved :: GNU General Public License v3 (GPLv3)
Classifier: Programming Language :: Python :: 2
Classifier: Development Status :: 4 - Beta
Classifier: Intended Audience :: Science/Research
Classifier: Natural Language :: English
Classifier: Operating System :: OS Independent
Classifier: Topic :: Scientific/Engineering :: Physics
Classifier: Topic :: Scientific/Engineering
Requires: numpy
Requires: matplotlib
Requires: scipy
